registry_downloader/__init__.py
registry_downloader/py.typed
registry_downloader/runner.py
registry_downloader/core/client.py
registry_downloader/core/progress.py
registry_downloader/core/threadpool.py
registry_downloader/downloaders/__init__.py
registry_downloader/downloaders/base.py
registry_downloader/downloaders/ee.py
registry_downloader/downloaders/fi.py
registry_downloader/downloaders/lv.py
registry_downloader-0.1.5.dist-info/METADATA
registry_downloader-0.1.5.dist-info/WHEEL
registry_downloader-0.1.5.dist-info/entry_points.txt
registry_downloader-0.1.5.dist-info/licenses/LICENSE
registry_downloader-0.1.5.dist-info/RECORD
