Metadata-Version: 2.3
Name: registry_downloader
Version: 0.1.5
Summary: Download & analyze business registry data
Project-URL: Homepage, https://github.com/salomartin/registry_downloader
Project-URL: Bug Tracker, https://github.com/salomartin/registry_downloader/issues
Author-email: Martin Salo <martin@salo.ee>
Keywords: business data,downloader,registry
Classifier: Development Status :: 3 - Alpha
Classifier: Intended Audience :: Developers
Classifier: Programming Language :: Python :: 3.12
Classifier: Topic :: Software Development :: Libraries :: Python Modules
Requires-Python: >=3.12
Requires-Dist: beautifulsoup4>=4.12.3
Requires-Dist: chardet>=5.2.0
Requires-Dist: httpx>=0.27.2
Requires-Dist: tqdm>=4.67.0
Requires-Dist: types-beautifulsoup4>=4.12.0.20241020
Requires-Dist: types-tqdm>=4.66.0.20240417
